neodigit_dyndns/__init__.py
neodigit_dyndns/__main__.py
neodigit_dyndns/dyndns.py
neodigit_dyndns-0.3.2.dist-info/LICENSE
neodigit_dyndns-0.3.2.dist-info/WHEEL
neodigit_dyndns-0.3.2.dist-info/METADATA
neodigit_dyndns-0.3.2.dist-info/RECORD
